quasemcryogui/__init__.py
quasemcryogui/quasemcryogui.py
quasemcryogui_tspspi-0.0.5.dist-info/LICENSE.md
quasemcryogui_tspspi-0.0.5.dist-info/METADATA
quasemcryogui_tspspi-0.0.5.dist-info/WHEEL
quasemcryogui_tspspi-0.0.5.dist-info/entry_points.txt
quasemcryogui_tspspi-0.0.5.dist-info/top_level.txt
quasemcryogui_tspspi-0.0.5.dist-info/RECORD
